odoo10_addon_l10n_nl_partner_salutation-10.0.1.0.0-py2.7-nspkg.pth
odoo/addons/l10n_nl_partner_salutation/README.rst
odoo/addons/l10n_nl_partner_salutation/__init__.py
odoo/addons/l10n_nl_partner_salutation/__manifest__.py
odoo/addons/l10n_nl_partner_salutation/data/res_partner_title.xml
odoo/addons/l10n_nl_partner_salutation/i18n/l10n_nl_partner_salutation.pot
odoo/addons/l10n_nl_partner_salutation/i18n/nl.po
odoo/addons/l10n_nl_partner_salutation/model/__init__.py
odoo/addons/l10n_nl_partner_salutation/model/res_partner.py
odoo/addons/l10n_nl_partner_salutation/model/res_partner_title.py
odoo/addons/l10n_nl_partner_salutation/tests/__init__.py
odoo/addons/l10n_nl_partner_salutation/tests/test_partner_name_splits.py
odoo/addons/l10n_nl_partner_salutation/view/res_partner.xml
odoo/addons/l10n_nl_partner_salutation/view/res_partner_title.xml
odoo10_addon_l10n_nl_partner_salutation-10.0.1.0.0.dist-info/DESCRIPTION.rst
odoo10_addon_l10n_nl_partner_salutation-10.0.1.0.0.dist-info/METADATA
odoo10_addon_l10n_nl_partner_salutation-10.0.1.0.0.dist-info/RECORD
odoo10_addon_l10n_nl_partner_salutation-10.0.1.0.0.dist-info/WHEEL
odoo10_addon_l10n_nl_partner_salutation-10.0.1.0.0.dist-info/metadata.json
odoo10_addon_l10n_nl_partner_salutation-10.0.1.0.0.dist-info/namespace_packages.txt
odoo10_addon_l10n_nl_partner_salutation-10.0.1.0.0.dist-info/top_level.txt
